slither/__init__.py
slither/__main__.py
slither/all_exceptions.py
slither/exceptions.py
slither/slither.py
slither/analyses/__init__.py
slither/analyses/data_dependency/__init__.py
slither/analyses/data_dependency/data_dependency.py
slither/analyses/evm/__init__.py
slither/analyses/evm/convert.py
slither/analyses/evm/evm_cfg_builder.py
slither/analyses/write/__init__.py
slither/analyses/write/are_variables_written.py
slither/core/__init__.py
slither/core/compilation_unit.py
slither/core/exceptions.py
slither/core/slither_core.py
slither/core/cfg/__init__.py
slither/core/cfg/node.py
slither/core/cfg/scope.py
slither/core/context/__init__.py
slither/core/context/context.py
slither/core/declarations/__init__.py
slither/core/declarations/contract.py
slither/core/declarations/contract_level.py
slither/core/declarations/custom_error.py
slither/core/declarations/custom_error_contract.py
slither/core/declarations/custom_error_top_level.py
slither/core/declarations/enum.py
slither/core/declarations/enum_contract.py
slither/core/declarations/enum_top_level.py
slither/core/declarations/event.py
slither/core/declarations/event_contract.py
slither/core/declarations/event_top_level.py
slither/core/declarations/function.py
slither/core/declarations/function_contract.py
slither/core/declarations/function_top_level.py
slither/core/declarations/import_directive.py
slither/core/declarations/modifier.py
slither/core/declarations/pragma_directive.py
slither/core/declarations/solidity_import_placeholder.py
slither/core/declarations/solidity_variables.py
slither/core/declarations/structure.py
slither/core/declarations/structure_contract.py
slither/core/declarations/structure_top_level.py
slither/core/declarations/top_level.py
slither/core/declarations/using_for_top_level.py
slither/core/dominators/__init__.py
slither/core/dominators/node_dominator_tree.py
slither/core/dominators/utils.py
slither/core/expressions/__init__.py
slither/core/expressions/assignment_operation.py
uschunter-0.0.1.dist-info/licenses/LICENSE
uschunter-0.0.1.dist-info/METADATA
uschunter-0.0.1.dist-info/WHEEL
uschunter-0.0.1.dist-info/entry_points.txt
uschunter-0.0.1.dist-info/top_level.txt
uschunter-0.0.1.dist-info/RECORD
