Metadata-Version: 2.4
Name: uschunter
Version: 0.0.1
Summary: Fork of Slither with USCHunter features
Home-page: 
Author: 
License: AGPL-3.0
Requires-Python: >=3.8
License-File: LICENSE
Requires-Dist: packaging
Requires-Dist: prettytable>=3.10.2
Requires-Dist: pycryptodome>=3.4.6
Requires-Dist: crytic-compile<0.4.0,>=0.3.9
Requires-Dist: web3<8,>=7.10
Requires-Dist: eth-abi>=5.0.1
Requires-Dist: eth-typing>=5.0.0
Requires-Dist: eth-utils>=5.0.0
Provides-Extra: lint
Requires-Dist: black==22.3.0; extra == "lint"
Requires-Dist: pylint==3.0.3; extra == "lint"
Provides-Extra: test
Requires-Dist: pytest; extra == "test"
Requires-Dist: pytest-cov; extra == "test"
Requires-Dist: pytest-xdist; extra == "test"
Requires-Dist: deepdiff; extra == "test"
Requires-Dist: orderly-set==5.3.2; extra == "test"
Requires-Dist: numpy; extra == "test"
Requires-Dist: coverage[toml]; extra == "test"
Requires-Dist: filelock; extra == "test"
Requires-Dist: pytest-insta; extra == "test"
Provides-Extra: doc
Requires-Dist: pdoc; extra == "doc"
Provides-Extra: dev
Requires-Dist: slither-analyzer[doc,lint,test]; extra == "dev"
Requires-Dist: openai; extra == "dev"
Dynamic: description
Dynamic: description-content-type
Dynamic: license
Dynamic: license-file
Dynamic: provides-extra
Dynamic: requires-dist
Dynamic: requires-python
Dynamic: summary
